CHANGES.md
CONTRIBUTING.md
Dockerfile
LICENSE
MANIFEST.in
README.md
requirements-dev.txt
requirements.txt
setup.py
tox.ini
fig/__init__.py
fig/container.py
fig/progress_stream.py
fig/project.py
fig/service.py
fig.egg-info/PKG-INFO
fig.egg-info/SOURCES.txt
fig.egg-info/dependency_links.txt
fig.egg-info/entry_points.txt
fig.egg-info/requires.txt
fig.egg-info/top_level.txt
fig/cli/__init__.py
fig/cli/colors.py
fig/cli/command.py
fig/cli/docker_client.py
fig/cli/docopt_command.py
fig/cli/errors.py
fig/cli/formatter.py
fig/cli/log_printer.py
fig/cli/main.py
fig/cli/multiplexer.py
fig/cli/utils.py
fig/cli/verbose_proxy.py