Metadata-Version: 1.0
Name: fig
Version: 1.0.1
Summary: Fast, isolated development environments using Docker
Home-page: http://www.fig.sh/
Author: Docker, Inc.
Author-email: UNKNOWN
License: Apache License 2.0
Platform: UNKNOWN
